[
  {
    "listing": "/Pages/about-us.html",
    "items": []
  },
  {
    "listing": "/Pages/Datasets/index.html",
    "items": []
  },
  {
    "listing": "/Local Only/Pages_old_replaced 05.11.2025/Datasets/Freely-Accessible/index.html",
    "items": []
  },
  {
    "listing": "/Local Only/Pages_old_replaced 05.11.2025/Resources/International/index.html",
    "items": []
  },
  {
    "listing": "/Local Only/Pages_old_replaced 05.11.2025/Resources/YSPH/index.html",
    "items": []
  },
  {
    "listing": "/Local Only/Pages_old_replaced 05.11.2025/Resources/index.html",
    "items": []
  },
  {
    "listing": "/Local Only/Pages_old_replaced 05.11.2025/Resources/YSM/index.html",
    "items": []
  },
  {
    "listing": "/Local Only/Pages_old_replaced 05.11.2025/Resources/Yale University/index.html",
    "items": []
  },
  {
    "listing": "/Local Only/Pages_old_replaced 05.11.2025/Resources/National/index.html",
    "items": []
  },
  {
    "listing": "/Local Only/Pages_old_replaced 05.11.2025/Datasets/Restricted-Access/index.html",
    "items": []
  },
  {
    "listing": "/Local Only/Pages_old_replaced 05.11.2025/Datasets/License-Required/index.html",
    "items": []
  },
  {
    "listing": "/Pages/Resources/index.html",
    "items": []
  }
]